trepublic2json/__init__.py
trepublic2json/__main__.py
trepublic2json/error.py
trepublic2json/parser.py
trepublic2json-0.3.7.dist-info/METADATA
trepublic2json-0.3.7.dist-info/WHEEL
trepublic2json-0.3.7.dist-info/entry_points.txt
trepublic2json-0.3.7.dist-info/licenses/LICENSE
trepublic2json-0.3.7.dist-info/RECORD
