Metadata-Version: 2.1
Name: trepublic2json
Version: 0.3.7
Summary: Parse and convert Invoice PDFs from Trade republic to JSON.
Project-URL: Source, https://github.com/ucyo/trepublic2json
Author-email: ucyo <cayoglu@me.com>
License-Expression: MIT
License-File: LICENSE
Keywords: json,parser,pdf,trade republic
Classifier: Development Status :: 3 - Alpha
Classifier: Topic :: File Formats
Classifier: Topic :: File Formats :: JSON
Requires-Python: >=3.8
Requires-Dist: pypdf>=4.1.0
